CHANGES.txt
LICENSE.txt
MANIFEST.in
README.txt
bootstrap.py
setup.py
src/s01/__init__.py
src/s01.scrapy.egg-info/PKG-INFO
src/s01.scrapy.egg-info/SOURCES.txt
src/s01.scrapy.egg-info/dependency_links.txt
src/s01.scrapy.egg-info/entry_points.txt
src/s01.scrapy.egg-info/namespace_packages.txt
src/s01.scrapy.egg-info/not-zip-safe
src/s01.scrapy.egg-info/requires.txt
src/s01.scrapy.egg-info/top_level.txt
src/s01/scrapy/README.txt
src/s01/scrapy/__init__.py
src/s01/scrapy/cmdline.py
src/s01/scrapy/converter.py
src/s01/scrapy/converter.txt
src/s01/scrapy/exporter.py
src/s01/scrapy/fieldproperty.py
src/s01/scrapy/item.py
src/s01/scrapy/log.py
src/s01/scrapy/script.py
src/s01/scrapy/tests.py
src/s01/scrapy/util.py
src/s01/scrapy/recipe/README.txt
src/s01/scrapy/recipe/__init__.py
src/s01/scrapy/recipe/tests.py